togglstandup/__init__.py
togglstandup/__main__.py
togglstandup/__version__.py
togglstandup/cli.py
toggl_standup-2021.12.1.dist-info/entry_points.txt
toggl_standup-2021.12.1.dist-info/WHEEL
toggl_standup-2021.12.1.dist-info/METADATA
toggl_standup-2021.12.1.dist-info/RECORD
