Metadata-Version: 2.1
Name: toggl-standup
Version: 2021.12.1
Summary: Removes the pain of using Toggl with Geekbot
Home-page: https://github.com/jefftriplett/toggl-standup
License: BSD-3-Clause
Author: Jeff Triplett
Author-email: jeff.triplett@gmail.com
Requires-Python: >=3.9,<4.0
Classifier: Intended Audience :: Developers
Classifier: License :: OSI Approved :: BSD License
Classifier: Natural Language :: English
Classifier: Programming Language :: Python
Classifier: Programming Language :: Python :: 3
Classifier: Programming Language :: Python :: 3.10
Classifier: Programming Language :: Python :: 3.6
Classifier: Programming Language :: Python :: 3.7
Classifier: Programming Language :: Python :: 3.8
Classifier: Programming Language :: Python :: 3.9
Requires-Dist: click (>=7.1.1,<8.0.0)
Requires-Dist: humanfriendly (>=10.0,<11.0)
Requires-Dist: maya (>=0.6.1,<0.7.0)
Requires-Dist: rich (>=10.15.2,<11.0.0)
Requires-Dist: togglwrapper (>=2.0.0,<3.0.0)
Requires-Dist: typer (>=0.4.0,<0.5.0)
Project-URL: Documentation, https://github.com/jefftriplett/toggl-standup
Project-URL: Repository, https://github.com/jefftriplett/toggl-standup
